scriptoria/__init__.py
scriptoria/codex.py
scriptoria-0.0.2.dist-info/LICENSE
scriptoria-0.0.2.dist-info/METADATA
scriptoria-0.0.2.dist-info/WHEEL
scriptoria-0.0.2.dist-info/top_level.txt
scriptoria-0.0.2.dist-info/RECORD
