Metadata-Version: 2.1
Name: scriptoria
Version: 0.0.2
Summary: Aufschreibesystem 2000
Home-page: https://github.com/seancska/corpuswork/scriptoria
Author: Sean Bethard
Author-email: sean@seanbethard.com
License: License :: OSI Approved :: Apache Software License
Platform: UNKNOWN
